{
  "artist_id": "1WVGbBnzZ5WLZ2PfesIHik",
  "artist_name": "Cassandra Jenkins",
  "tracks": [
    {
      "track_name": "Michelangelo (demo)",
      "track_popularity": 6,
      "track_preview": "https://p.scdn.co/mp3-preview/ab6771bbf76d12b0a40d0660cb878212695a4d62?cid=5bae1e05720d486a8bef2310f63cdb05",
      "track_duration": 251946,
      "track_danceability": 0.585,
      "track_energy": 0.265,
      "track_key": 7,
      "track_loudness": -12.685,
      "track_mode": 1,
      "track_speechiness": 0.0286,
      "track_acousticness": 0.873,
      "track_instrumentalness": 0.00617,
      "track_liveness": 0.224,
      "track_valence": 0.333,
      "track_tempo": 130.073,
      "track_time_signature": 4
    },
    {
      "track_name": "New Bikini (first take)",
      "track_popularity": 7,
      "track_preview": "https://p.scdn.co/mp3-preview/31f88204c8110fe89de291c9c5db48f7ce95b0e5?cid=5bae1e05720d486a8bef2310f63cdb05",
      "track_duration": 253248,
      "track_danceability": 0.333,
      "track_energy": 0.252,
      "track_key": 2,
      "track_loudness": -15.618,
      "track_mode": 1,
      "track_speechiness": 0.0355,
      "track_acousticness": 0.213,
      "track_instrumentalness": 0.922,
      "track_liveness": 0.158,
      "track_valence": 0.198,
      "track_tempo": 124.855,
      "track_time_signature": 4
    },
    {
      "track_name": "Crosshairs (interlude)",
      "track_popularity": 18,
      "track_preview": "https://p.scdn.co/mp3-preview/2dfffd942d7cb710e1beffdee51dac682ce31faf?cid=5bae1e05720d486a8bef2310f63cdb05",
      "track_duration": 108320,
      "track_danceability": 0.316,
      "track_energy": 0.309,
      "track_key": 2,
      "track_loudness": -13.253,
      "track_mode": 1,
      "track_speechiness": 0.0507,
      "track_acousticness": 0.607,
      "track_instrumentalness": 0.853,
      "track_liveness": 0.0887,
      "track_valence": 0.0396,
      "track_tempo": 144.791,
      "track_time_signature": 4
    },
    {
      "track_name": "Ms. Cassandra",
      "track_popularity": 8,
      "track_preview": "https://p.scdn.co/mp3-preview/486f48c219c7238cfb86e7341e1d5af1e2dde111?cid=5bae1e05720d486a8bef2310f63cdb05",
      "track_duration": 48000,
      "track_danceability": 0.563,
      "track_energy": 0.263,
      "track_key": 7,
      "track_loudness": -19.839,
      "track_mode": 1,
      "track_speechiness": 0.374,
      "track_acousticness": 0.993,
      "track_instrumentalness": 0.367,
      "track_liveness": 0.106,
      "track_valence": 0.74,
      "track_tempo": 72.748,
      "track_time_signature": 3
    },
    {
      "track_name": "American Spirits",
      "track_popularity": 13,
      "track_preview": "https://p.scdn.co/mp3-preview/2bea367eb75eac95577e028fe7cf6429453a41bf?cid=5bae1e05720d486a8bef2310f63cdb05",
      "track_duration": 283008,
      "track_danceability": 0.24,
      "track_energy": 0.158,
      "track_key": 7,
      "track_loudness": -20.365,
      "track_mode": 1,
      "track_speechiness": 0.0372,
      "track_acousticness": 0.683,
      "track_instrumentalness": 0.703,
      "track_liveness": 0.0788,
      "track_valence": 0.178,
      "track_tempo": 83.163,
      "track_time_signature": 4
    },
    {
      "track_name": "Hailey (premix)",
      "track_popularity": 9,
      "track_preview": "https://p.scdn.co/mp3-preview/2534fd201803491ff97aea3c3522b052ee5e3c48?cid=5bae1e05720d486a8bef2310f63cdb05",
      "track_duration": 186368,
      "track_danceability": 0.737,
      "track_energy": 0.529,
      "track_key": 9,
      "track_loudness": -10.249,
      "track_mode": 1,
      "track_speechiness": 0.0352,
      "track_acousticness": 0.292,
      "track_instrumentalness": 0.926,
      "track_liveness": 0.157,
      "track_valence": 0.706,
      "track_tempo": 126.034,
      "track_time_signature": 4
    },
    {
      "track_name": "Ambiguous Norway (instrumental)",
      "track_popularity": 24,
      "track_preview": "https://p.scdn.co/mp3-preview/13701a60d1221bb41a0ad49ff2b556c8657e6e87?cid=5bae1e05720d486a8bef2310f63cdb05",
      "track_duration": 102826,
      "track_danceability": 0.173,
      "track_energy": 0.183,
      "track_key": 4,
      "track_loudness": -18.898,
      "track_mode": 1,
      "track_speechiness": 0.0362,
      "track_acousticness": 0.891,
      "track_instrumentalness": 0.865,
      "track_liveness": 0.163,
      "track_valence": 0.101,
      "track_tempo": 118.558,
      "track_time_signature": 4
    },
    {
      "track_name": "Hard Drive (security guard)",
      "track_popularity": 5,
      "track_preview": "https://p.scdn.co/mp3-preview/afe0aa17b77db1aa1fa1f1dec54d6eb612691e0d?cid=5bae1e05720d486a8bef2310f63cdb05",
      "track_duration": 280234,
      "track_danceability": 0.482,
      "track_energy": 0.768,
      "track_key": 9,
      "track_loudness": -12.916,
      "track_mode": 1,
      "track_speechiness": 0.201,
      "track_acousticness": 0.475,
      "track_instrumentalness": 0.00454,
      "track_liveness": 0.187,
      "track_valence": 0.621,
      "track_tempo": 106.956,
      "track_time_signature": 4
    },
    {
      "track_name": "Michelangelo (demo)",
      "track_popularity": 6,
      "track_preview": "https://p.scdn.co/mp3-preview/ab6771bbf76d12b0a40d0660cb878212695a4d62?cid=5bae1e05720d486a8bef2310f63cdb05",
      "track_duration": 251946,
      "track_danceability": 0.586,
      "track_energy": 0.266,
      "track_key": 7,
      "track_loudness": -12.686,
      "track_mode": 1,
      "track_speechiness": 0.0286,
      "track_acousticness": 0.869,
      "track_instrumentalness": 0.00638,
      "track_liveness": 0.223,
      "track_valence": 0.329,
      "track_tempo": 129.791,
      "track_time_signature": 4
    },
    {
      "track_name": "New Bikini (first take)",
      "track_popularity": 7,
      "track_preview": "https://p.scdn.co/mp3-preview/31f88204c8110fe89de291c9c5db48f7ce95b0e5?cid=5bae1e05720d486a8bef2310f63cdb05",
      "track_duration": 253248,
      "track_danceability": 0.235,
      "track_energy": 0.253,
      "track_key": 2,
      "track_loudness": -15.621,
      "track_mode": 1,
      "track_speechiness": 0.0338,
      "track_acousticness": 0.208,
      "track_instrumentalness": 0.923,
      "track_liveness": 0.158,
      "track_valence": 0.221,
      "track_tempo": 179.457,
      "track_time_signature": 3
    },
    {
      "track_name": "Crosshairs (interlude)",
      "track_popularity": 18,
      "track_preview": "https://p.scdn.co/mp3-preview/2dfffd942d7cb710e1beffdee51dac682ce31faf?cid=5bae1e05720d486a8bef2310f63cdb05",
      "track_duration": 108320,
      "track_danceability": 0.369,
      "track_energy": 0.307,
      "track_key": 2,
      "track_loudness": -13.248,
      "track_mode": 1,
      "track_speechiness": 0.0514,
      "track_acousticness": 0.592,
      "track_instrumentalness": 0.866,
      "track_liveness": 0.0887,
      "track_valence": 0.0384,
      "track_tempo": 144.598,
      "track_time_signature": 4
    },
    {
      "track_name": "Hailey (premix)",
      "track_popularity": 9,
      "track_preview": "https://p.scdn.co/mp3-preview/2534fd201803491ff97aea3c3522b052ee5e3c48?cid=5bae1e05720d486a8bef2310f63cdb05",
      "track_duration": 186368,
      "track_danceability": 0.74,
      "track_energy": 0.526,
      "track_key": 9,
      "track_loudness": -10.254,
      "track_mode": 1,
      "track_speechiness": 0.0358,
      "track_acousticness": 0.292,
      "track_instrumentalness": 0.92,
      "track_liveness": 0.157,
      "track_valence": 0.726,
      "track_tempo": 125.989,
      "track_time_signature": 4
    },
    {
      "track_name": "Ambiguous Norway (instrumental)",
      "track_popularity": 24,
      "track_preview": "https://p.scdn.co/mp3-preview/13701a60d1221bb41a0ad49ff2b556c8657e6e87?cid=5bae1e05720d486a8bef2310f63cdb05",
      "track_duration": 102826,
      "track_danceability": 0.199,
      "track_energy": 0.183,
      "track_key": 4,
      "track_loudness": -18.859,
      "track_mode": 1,
      "track_speechiness": 0.0325,
      "track_acousticness": 0.894,
      "track_instrumentalness": 0.882,
      "track_liveness": 0.168,
      "track_valence": 0.0971,
      "track_tempo": 84.186,
      "track_time_signature": 5
    },
    {
      "track_name": "Hard Drive (security guard)",
      "track_popularity": 5,
      "track_preview": "https://p.scdn.co/mp3-preview/afe0aa17b77db1aa1fa1f1dec54d6eb612691e0d?cid=5bae1e05720d486a8bef2310f63cdb05",
      "track_duration": 280234,
      "track_danceability": 0.442,
      "track_energy": 0.769,
      "track_key": 2,
      "track_loudness": -12.918,
      "track_mode": 1,
      "track_speechiness": 0.204,
      "track_acousticness": 0.483,
      "track_instrumentalness": 0.00366,
      "track_liveness": 0.159,
      "track_valence": 0.625,
      "track_tempo": 106.797,
      "track_time_signature": 4
    },
    {
      "track_name": "Michelangelo",
      "track_popularity": 37,
      "track_preview": "https://p.scdn.co/mp3-preview/8b507dbe8ce4604175a58ea262b85b2013ffbf81?cid=5bae1e05720d486a8bef2310f63cdb05",
      "track_duration": 209826,
      "track_danceability": 0.564,
      "track_energy": 0.368,
      "track_key": 7,
      "track_loudness": -10.228,
      "track_mode": 1,
      "track_speechiness": 0.0281,
      "track_acousticness": 0.587,
      "track_instrumentalness": 0.681,
      "track_liveness": 0.18,
      "track_valence": 0.544,
      "track_tempo": 139.01,
      "track_time_signature": 4
    },
    {
      "track_name": "New Bikini",
      "track_popularity": 27,
      "track_preview": "https://p.scdn.co/mp3-preview/5ba438733a0c2e33019dfa4170b1226921d35749?cid=5bae1e05720d486a8bef2310f63cdb05",
      "track_duration": 262092,
      "track_danceability": 0.256,
      "track_energy": 0.352,
      "track_key": 7,
      "track_loudness": -13.562,
      "track_mode": 1,
      "track_speechiness": 0.0478,
      "track_acousticness": 0.688,
      "track_instrumentalness": 0.0017,
      "track_liveness": 0.11,
      "track_valence": 0.203,
      "track_tempo": 178.159,
      "track_time_signature": 3
    },
    {
      "track_name": "Hard Drive",
      "track_popularity": 36,
      "track_preview": "https://p.scdn.co/mp3-preview/ca23efc718315586db70a3e188bcb7c757e94df9?cid=5bae1e05720d486a8bef2310f63cdb05",
      "track_duration": 327440,
      "track_danceability": 0.581,
      "track_energy": 0.631,
      "track_key": 9,
      "track_loudness": -11.485,
      "track_mode": 1,
      "track_speechiness": 0.0371,
      "track_acousticness": 0.32,
      "track_instrumentalness": 0.516,
      "track_liveness": 0.0739,
      "track_valence": 0.584,
      "track_tempo": 107.0,
      "track_time_signature": 4
    },
    {
      "track_name": "Crosshairs",
      "track_popularity": 28,
      "track_preview": "https://p.scdn.co/mp3-preview/b7e4243c3453cc0a2cb347d6ad3d5addf06f6491?cid=5bae1e05720d486a8bef2310f63cdb05",
      "track_duration": 243773,
      "track_danceability": 0.531,
      "track_energy": 0.297,
      "track_key": 2,
      "track_loudness": -11.793,
      "track_mode": 1,
      "track_speechiness": 0.0288,
      "track_acousticness": 0.506,
      "track_instrumentalness": 0.462,
      "track_liveness": 0.125,
      "track_valence": 0.409,
      "track_tempo": 71.958,
      "track_time_signature": 4
    },
    {
      "track_name": "Ambiguous Norway",
      "track_popularity": 23,
      "track_preview": "https://p.scdn.co/mp3-preview/20b28d8ef7c953d6096e3d37467c41fef0726da3?cid=5bae1e05720d486a8bef2310f63cdb05",
      "track_duration": 260173,
      "track_danceability": 0.335,
      "track_energy": 0.183,
      "track_key": 4,
      "track_loudness": -16.004,
      "track_mode": 1,
      "track_speechiness": 0.0315,
      "track_acousticness": 0.762,
      "track_instrumentalness": 0.629,
      "track_liveness": 0.11,
      "track_valence": 0.116,
      "track_tempo": 114.282,
      "track_time_signature": 4
    },
    {
      "track_name": "Hailey",
      "track_popularity": 22,
      "track_preview": "https://p.scdn.co/mp3-preview/308a838b0ac9b7550dda7a74d382ed5904f8c200?cid=5bae1e05720d486a8bef2310f63cdb05",
      "track_duration": 173346,
      "track_danceability": 0.513,
      "track_energy": 0.0601,
      "track_key": 9,
      "track_loudness": -18.552,
      "track_mode": 1,
      "track_speechiness": 0.033,
      "track_acousticness": 0.889,
      "track_instrumentalness": 0.257,
      "track_liveness": 0.294,
      "track_valence": 0.318,
      "track_tempo": 108.042,
      "track_time_signature": 4
    },
    {
      "track_name": "The Ramble",
      "track_popularity": 25,
      "track_preview": "https://p.scdn.co/mp3-preview/daa1e5d1dcd0d988a2e024a6906f559142f7924a?cid=5bae1e05720d486a8bef2310f63cdb05",
      "track_duration": 428120,
      "track_danceability": 0.133,
      "track_energy": 0.296,
      "track_key": 2,
      "track_loudness": -16.968,
      "track_mode": 1,
      "track_speechiness": 0.0422,
      "track_acousticness": 0.855,
      "track_instrumentalness": 0.893,
      "track_liveness": 0.122,
      "track_valence": 0.142,
      "track_tempo": 76.933,
      "track_time_signature": 4
    },
    {
      "track_name": "Candy Crane",
      "track_popularity": 15,
      "track_preview": "https://p.scdn.co/mp3-preview/af657c86a70283e694d96def85b52c0e95d7580a?cid=5bae1e05720d486a8bef2310f63cdb05",
      "track_duration": 215784,
      "track_danceability": 0.636,
      "track_energy": 0.319,
      "track_key": 5,
      "track_loudness": -11.191,
      "track_mode": 1,
      "track_speechiness": 0.0373,
      "track_acousticness": 0.583,
      "track_instrumentalness": 0.00718,
      "track_liveness": 0.234,
      "track_valence": 0.176,
      "track_tempo": 72.029,
      "track_time_signature": 3
    },
    {
      "track_name": "Tennessee Waltz",
      "track_popularity": 13,
      "track_preview": "https://p.scdn.co/mp3-preview/d0159af5e9108d83bc938414c08df4da8687f4ca?cid=5bae1e05720d486a8bef2310f63cdb05",
      "track_duration": 225952,
      "track_danceability": 0.62,
      "track_energy": 0.573,
      "track_key": 0,
      "track_loudness": -8.714,
      "track_mode": 1,
      "track_speechiness": 0.0296,
      "track_acousticness": 0.212,
      "track_instrumentalness": 0.285,
      "track_liveness": 0.159,
      "track_valence": 0.471,
      "track_tempo": 120.947,
      "track_time_signature": 4
    },
    {
      "track_name": "Jan Lee Jansen",
      "track_popularity": 10,
      "track_preview": "https://p.scdn.co/mp3-preview/22d398d53bb814818c8a15a59d0a35864a867940?cid=5bae1e05720d486a8bef2310f63cdb05",
      "track_duration": 197485,
      "track_danceability": 0.571,
      "track_energy": 0.358,
      "track_key": 9,
      "track_loudness": -10.828,
      "track_mode": 1,
      "track_speechiness": 0.0385,
      "track_acousticness": 0.379,
      "track_instrumentalness": 0.0229,
      "track_liveness": 0.105,
      "track_valence": 0.128,
      "track_tempo": 119.918,
      "track_time_signature": 4
    },
    {
      "track_name": "Shame",
      "track_popularity": 11,
      "track_preview": "https://p.scdn.co/mp3-preview/f572297d9ffa2d20ad045bb9440c5c1ebe11e5f7?cid=5bae1e05720d486a8bef2310f63cdb05",
      "track_duration": 341741,
      "track_danceability": 0.429,
      "track_energy": 0.531,
      "track_key": 4,
      "track_loudness": -9.085,
      "track_mode": 1,
      "track_speechiness": 0.0321,
      "track_acousticness": 0.244,
      "track_instrumentalness": 0.266,
      "track_liveness": 0.155,
      "track_valence": 0.265,
      "track_tempo": 142.192,
      "track_time_signature": 4
    },
    {
      "track_name": "Red Lips",
      "track_popularity": 28,
      "track_preview": "https://p.scdn.co/mp3-preview/8da25a7b90d2ebe55b0bd15647e8d4f95a48cd46?cid=5bae1e05720d486a8bef2310f63cdb05",
      "track_duration": 213484,
      "track_danceability": 0.412,
      "track_energy": 0.507,
      "track_key": 11,
      "track_loudness": -8.552,
      "track_mode": 0,
      "track_speechiness": 0.0302,
      "track_acousticness": 0.18,
      "track_instrumentalness": 0.0297,
      "track_liveness": 0.0949,
      "track_valence": 0.063,
      "track_tempo": 83.036,
      "track_time_signature": 4
    },
    {
      "track_name": "Disappearing",
      "track_popularity": 11,
      "track_preview": "https://p.scdn.co/mp3-preview/e274296a7eefa3e28050e3c71ccd180705bfaa3f?cid=5bae1e05720d486a8bef2310f63cdb05",
      "track_duration": 218297,
      "track_danceability": 0.422,
      "track_energy": 0.442,
      "track_key": 0,
      "track_loudness": -11.163,
      "track_mode": 1,
      "track_speechiness": 0.032,
      "track_acousticness": 0.615,
      "track_instrumentalness": 0.584,
      "track_liveness": 0.109,
      "track_valence": 0.258,
      "track_tempo": 72.138,
      "track_time_signature": 1
    },
    {
      "track_name": "Hotel Lullaby",
      "track_popularity": 8,
      "track_preview": "https://p.scdn.co/mp3-preview/d06ef3e22c355747a41ecf12252f6757405cbcc1?cid=5bae1e05720d486a8bef2310f63cdb05",
      "track_duration": 188085,
      "track_danceability": 0.459,
      "track_energy": 0.459,
      "track_key": 2,
      "track_loudness": -10.866,
      "track_mode": 1,
      "track_speechiness": 0.0316,
      "track_acousticness": 0.781,
      "track_instrumentalness": 0.367,
      "track_liveness": 0.13,
      "track_valence": 0.25,
      "track_tempo": 84.032,
      "track_time_signature": 4
    },
    {
      "track_name": "Honda's Well",
      "track_popularity": 8,
      "track_preview": "https://p.scdn.co/mp3-preview/7c191670ac0abd39073b31735c24df65bf1ccc6e?cid=5bae1e05720d486a8bef2310f63cdb05",
      "track_duration": 226130,
      "track_danceability": 0.524,
      "track_energy": 0.471,
      "track_key": 7,
      "track_loudness": -9.704,
      "track_mode": 1,
      "track_speechiness": 0.0331,
      "track_acousticness": 0.3,
      "track_instrumentalness": 0.676,
      "track_liveness": 0.132,
      "track_valence": 0.553,
      "track_tempo": 78.136,
      "track_time_signature": 4
    },
    {
      "track_name": "Disco Death Dance",
      "track_popularity": 9,
      "track_preview": "https://p.scdn.co/mp3-preview/5a63090ad7cdc0f282b610d67c08de9a08abe54b?cid=5bae1e05720d486a8bef2310f63cdb05",
      "track_duration": 184666,
      "track_danceability": 0.683,
      "track_energy": 0.394,
      "track_key": 2,
      "track_loudness": -11.981,
      "track_mode": 1,
      "track_speechiness": 0.0306,
      "track_acousticness": 0.628,
      "track_instrumentalness": 0.0599,
      "track_liveness": 0.109,
      "track_valence": 0.327,
      "track_tempo": 112.069,
      "track_time_signature": 4
    },
    {
      "track_name": "Some Time",
      "track_popularity": 8,
      "track_preview": "https://p.scdn.co/mp3-preview/1ca330eb75e04c5f7897e22f836a17246b4b9eaf?cid=5bae1e05720d486a8bef2310f63cdb05",
      "track_duration": 261610,
      "track_danceability": 0.436,
      "track_energy": 0.531,
      "track_key": 4,
      "track_loudness": -9.565,
      "track_mode": 1,
      "track_speechiness": 0.0251,
      "track_acousticness": 0.446,
      "track_instrumentalness": 0.456,
      "track_liveness": 0.15,
      "track_valence": 0.376,
      "track_tempo": 82.153,
      "track_time_signature": 4
    },
    {
      "track_name": "Halley",
      "track_popularity": 6,
      "track_preview": "https://p.scdn.co/mp3-preview/8f56d187dbd78b23f1ddf1eee00e8df1b5ddb4ee?cid=5bae1e05720d486a8bef2310f63cdb05",
      "track_duration": 218511,
      "track_danceability": 0.526,
      "track_energy": 0.137,
      "track_key": 3,
      "track_loudness": -12.876,
      "track_mode": 1,
      "track_speechiness": 0.0689,
      "track_acousticness": 0.874,
      "track_instrumentalness": 0.000161,
      "track_liveness": 0.419,
      "track_valence": 0.52,
      "track_tempo": 111.32,
      "track_time_signature": 3
    },
    {
      "track_name": "Pygmalion",
      "track_popularity": 28,
      "track_preview": "https://p.scdn.co/mp3-preview/3a971ac4f7606b4eb0724f32879ced4c3bd32d7b?cid=5bae1e05720d486a8bef2310f63cdb05",
      "track_duration": 150251,
      "track_danceability": 0.396,
      "track_energy": 0.427,
      "track_key": 4,
      "track_loudness": -9.196,
      "track_mode": 0,
      "track_speechiness": 0.0302,
      "track_acousticness": 0.335,
      "track_instrumentalness": 0.327,
      "track_liveness": 0.107,
      "track_valence": 0.19,
      "track_tempo": 168.402,
      "track_time_signature": 4
    },
    {
      "track_name": "It's You",
      "track_popularity": 13,
      "track_preview": "https://p.scdn.co/mp3-preview/c21b88c9c86d6c2e8d5e99413ec8e691b5217cce?cid=5bae1e05720d486a8bef2310f63cdb05",
      "track_duration": 256252,
      "track_danceability": 0.314,
      "track_energy": 0.194,
      "track_key": 5,
      "track_loudness": -17.271,
      "track_mode": 1,
      "track_speechiness": 0.035,
      "track_acousticness": 0.934,
      "track_instrumentalness": 0.0351,
      "track_liveness": 0.114,
      "track_valence": 0.0849,
      "track_tempo": 68.408,
      "track_time_signature": 3
    },
    {
      "track_name": "Michelangelo",
      "track_popularity": 37,
      "track_preview": "https://p.scdn.co/mp3-preview/8b507dbe8ce4604175a58ea262b85b2013ffbf81?cid=5bae1e05720d486a8bef2310f63cdb05",
      "track_duration": 209826,
      "track_danceability": 0.564,
      "track_energy": 0.368,
      "track_key": 7,
      "track_loudness": -10.228,
      "track_mode": 1,
      "track_speechiness": 0.0281,
      "track_acousticness": 0.587,
      "track_instrumentalness": 0.681,
      "track_liveness": 0.18,
      "track_valence": 0.544,
      "track_tempo": 139.01,
      "track_time_signature": 4
    },
    {
      "track_name": "Things to You",
      "track_popularity": 7,
      "track_preview": "https://p.scdn.co/mp3-preview/26b51b2b96aa096f507c10fad46f7e8d8d75fd89?cid=5bae1e05720d486a8bef2310f63cdb05",
      "track_duration": 182135,
      "track_danceability": 0.624,
      "track_energy": 0.561,
      "track_key": 0,
      "track_loudness": -8.568,
      "track_mode": 1,
      "track_speechiness": 0.025,
      "track_acousticness": 0.809,
      "track_instrumentalness": 0.00448,
      "track_liveness": 0.169,
      "track_valence": 0.516,
      "track_tempo": 107.954,
      "track_time_signature": 4
    },
    {
      "track_name": "Hotel Lullaby (Acoustic)",
      "track_popularity": 1,
      "track_preview": "https://p.scdn.co/mp3-preview/57c4bc9b0fee7474d897d0d4d01609729cf85b0d?cid=5bae1e05720d486a8bef2310f63cdb05",
      "track_duration": 194667,
      "track_danceability": 0.303,
      "track_energy": 0.273,
      "track_key": 2,
      "track_loudness": -13.206,
      "track_mode": 1,
      "track_speechiness": 0.0309,
      "track_acousticness": 0.916,
      "track_instrumentalness": 0.00498,
      "track_liveness": 0.152,
      "track_valence": 0.231,
      "track_tempo": 167.566,
      "track_time_signature": 4
    },
    {
      "track_name": "Red Lips - Audiotree Live Version",
      "track_popularity": 1,
      "track_preview": "https://p.scdn.co/mp3-preview/65ed216cf06d8978e9ed1898503db19c5e73c4f8?cid=5bae1e05720d486a8bef2310f63cdb05",
      "track_duration": 203114,
      "track_danceability": 0.494,
      "track_energy": 0.285,
      "track_key": 1,
      "track_loudness": -14.595,
      "track_mode": 0,
      "track_speechiness": 0.0245,
      "track_acousticness": 0.0257,
      "track_instrumentalness": 0.932,
      "track_liveness": 0.137,
      "track_valence": 0.106,
      "track_tempo": 86.428,
      "track_time_signature": 4
    },
    {
      "track_name": "Candy Crane - Audiotree Live Version",
      "track_popularity": 0,
      "track_preview": "https://p.scdn.co/mp3-preview/05b09b44ba0b9e3757b34d9a0771c8f645702453?cid=5bae1e05720d486a8bef2310f63cdb05",
      "track_duration": 212616,
      "track_danceability": 0.442,
      "track_energy": 0.298,
      "track_key": 5,
      "track_loudness": -14.543,
      "track_mode": 1,
      "track_speechiness": 0.0331,
      "track_acousticness": 0.00979,
      "track_instrumentalness": 0.0642,
      "track_liveness": 0.134,
      "track_valence": 0.167,
      "track_tempo": 71.377,
      "track_time_signature": 3
    },
    {
      "track_name": "Hotel Lullaby - Audiotree Live Version",
      "track_popularity": 0,
      "track_preview": "https://p.scdn.co/mp3-preview/7e8416ea29d48cd2a1d742625c125b2a072814ac?cid=5bae1e05720d486a8bef2310f63cdb05",
      "track_duration": 196669,
      "track_danceability": 0.355,
      "track_energy": 0.197,
      "track_key": 2,
      "track_loudness": -15.962,
      "track_mode": 1,
      "track_speechiness": 0.0295,
      "track_acousticness": 0.153,
      "track_instrumentalness": 0.178,
      "track_liveness": 0.107,
      "track_valence": 0.104,
      "track_tempo": 84.496,
      "track_time_signature": 4
    },
    {
      "track_name": "Rose - Audiotree Live Version",
      "track_popularity": 0,
      "track_preview": "https://p.scdn.co/mp3-preview/afd5a208a7385393578754a12848b81a94926c5f?cid=5bae1e05720d486a8bef2310f63cdb05",
      "track_duration": 312528,
      "track_danceability": 0.577,
      "track_energy": 0.322,
      "track_key": 11,
      "track_loudness": -13.845,
      "track_mode": 0,
      "track_speechiness": 0.028,
      "track_acousticness": 0.203,
      "track_instrumentalness": 0.627,
      "track_liveness": 0.208,
      "track_valence": 0.337,
      "track_tempo": 129.495,
      "track_time_signature": 4
    },
    {
      "track_name": "Botanica - Audiotree Live Version",
      "track_popularity": 0,
      "track_preview": "https://p.scdn.co/mp3-preview/791258fd7dd5dff2bee1eeb2d1c7ff9ae2ef7499?cid=5bae1e05720d486a8bef2310f63cdb05",
      "track_duration": 170080,
      "track_danceability": 0.155,
      "track_energy": 0.0735,
      "track_key": 2,
      "track_loudness": -17.069,
      "track_mode": 1,
      "track_speechiness": 0.0351,
      "track_acousticness": 0.944,
      "track_instrumentalness": 0.000517,
      "track_liveness": 0.231,
      "track_valence": 0.138,
      "track_tempo": 58.679,
      "track_time_signature": 4
    },
    {
      "track_name": "Rose",
      "track_popularity": 4,
      "track_preview": "https://p.scdn.co/mp3-preview/5cddc2506399d49fe133f0e5ab1ec49b90f5ec02?cid=5bae1e05720d486a8bef2310f63cdb05",
      "track_duration": 373116,
      "track_danceability": 0.567,
      "track_energy": 0.692,
      "track_key": 4,
      "track_loudness": -10.437,
      "track_mode": 1,
      "track_speechiness": 0.0603,
      "track_acousticness": 0.32,
      "track_instrumentalness": 0.821,
      "track_liveness": 0.484,
      "track_valence": 0.534,
      "track_tempo": 127.441,
      "track_time_signature": 4
    },
    {
      "track_name": "Wild World",
      "track_popularity": 19,
      "track_preview": "https://p.scdn.co/mp3-preview/77ca8d6ed436b38f3156151d623d1fc6a52d999d?cid=5bae1e05720d486a8bef2310f63cdb05",
      "track_duration": 231517,
      "track_danceability": 0.506,
      "track_energy": 0.304,
      "track_key": 2,
      "track_loudness": -12.136,
      "track_mode": 1,
      "track_speechiness": 0.0332,
      "track_acousticness": 0.24,
      "track_instrumentalness": 0.00102,
      "track_liveness": 0.162,
      "track_valence": 0.141,
      "track_tempo": 119.455,
      "track_time_signature": 4
    },
    {
      "track_name": "Caterpillar",
      "track_popularity": 0,
      "track_preview": "https://p.scdn.co/mp3-preview/6eb7547b2c9a2e3ba0689fabd7a72ef3ef40cfe4?cid=5bae1e05720d486a8bef2310f63cdb05",
      "track_duration": 241093,
      "track_danceability": 0.175,
      "track_energy": 0.337,
      "track_key": 9,
      "track_loudness": -12.271,
      "track_mode": 1,
      "track_speechiness": 0.0369,
      "track_acousticness": 0.534,
      "track_instrumentalness": 0.675,
      "track_liveness": 0.343,
      "track_valence": 0.234,
      "track_tempo": 84.725,
      "track_time_signature": 5
    },
    {
      "track_name": "The Bird",
      "track_popularity": 0,
      "track_preview": "https://p.scdn.co/mp3-preview/682d41aff106ab396934131c12a5c6cd0a2a8a50?cid=5bae1e05720d486a8bef2310f63cdb05",
      "track_duration": 212133,
      "track_danceability": 0.5,
      "track_energy": 0.11,
      "track_key": 4,
      "track_loudness": -17.28,
      "track_mode": 0,
      "track_speechiness": 0.0369,
      "track_acousticness": 0.922,
      "track_instrumentalness": 0.00271,
      "track_liveness": 0.112,
      "track_valence": 0.106,
      "track_tempo": 127.302,
      "track_time_signature": 4
    },
    {
      "track_name": "Motorcycle Mary",
      "track_popularity": 0,
      "track_preview": "https://p.scdn.co/mp3-preview/5ee0b140b47a5af31575b5cc292657faddf955ee?cid=5bae1e05720d486a8bef2310f63cdb05",
      "track_duration": 234320,
      "track_danceability": 0.527,
      "track_energy": 0.21,
      "track_key": 9,
      "track_loudness": -12.474,
      "track_mode": 1,
      "track_speechiness": 0.0257,
      "track_acousticness": 0.653,
      "track_instrumentalness": 0.0415,
      "track_liveness": 0.342,
      "track_valence": 0.0708,
      "track_tempo": 79.468,
      "track_time_signature": 3
    },
    {
      "track_name": "Up in Flames",
      "track_popularity": 0,
      "track_preview": "https://p.scdn.co/mp3-preview/3ec38290cb324eae16399bb08a96e654f36062b5?cid=5bae1e05720d486a8bef2310f63cdb05",
      "track_duration": 226466,
      "track_danceability": 0.322,
      "track_energy": 0.248,
      "track_key": 7,
      "track_loudness": -14.168,
      "track_mode": 0,
      "track_speechiness": 0.0293,
      "track_acousticness": 0.853,
      "track_instrumentalness": 0.763,
      "track_liveness": 0.138,
      "track_valence": 0.07,
      "track_tempo": 152.068,
      "track_time_signature": 4
    },
    {
      "track_name": "Telephone Ghost",
      "track_popularity": 0,
      "track_preview": "https://p.scdn.co/mp3-preview/9f0b2d954ccb0c806ed39525b0c27a801dd82a32?cid=5bae1e05720d486a8bef2310f63cdb05",
      "track_duration": 199786,
      "track_danceability": 0.516,
      "track_energy": 0.223,
      "track_key": 0,
      "track_loudness": -16.561,
      "track_mode": 1,
      "track_speechiness": 0.0258,
      "track_acousticness": 0.909,
      "track_instrumentalness": 0.703,
      "track_liveness": 0.11,
      "track_valence": 0.419,
      "track_tempo": 79.947,
      "track_time_signature": 4
    },
    {
      "track_name": "Birthday Song",
      "track_popularity": 0,
      "track_preview": "https://p.scdn.co/mp3-preview/c9336bd65d86fa456c68e9cd99b219a625e0b502?cid=5bae1e05720d486a8bef2310f63cdb05",
      "track_duration": 269760,
      "track_danceability": 0.465,
      "track_energy": 0.0414,
      "track_key": 2,
      "track_loudness": -18.413,
      "track_mode": 1,
      "track_speechiness": 0.0316,
      "track_acousticness": 0.969,
      "track_instrumentalness": 0.16,
      "track_liveness": 0.11,
      "track_valence": 0.0621,
      "track_tempo": 72.548,
      "track_time_signature": 4
    },
    {
      "track_name": "Perfect Day",
      "track_popularity": 3,
      "track_preview": "https://p.scdn.co/mp3-preview/dd2d30fccf7db8bec7068944a837f9ed69522f32?cid=5bae1e05720d486a8bef2310f63cdb05",
      "track_duration": 248496,
      "track_danceability": 0.306,
      "track_energy": 0.49,
      "track_key": 2,
      "track_loudness": -10.941,
      "track_mode": 1,
      "track_speechiness": 0.0313,
      "track_acousticness": 0.257,
      "track_instrumentalness": 0.00458,
      "track_liveness": 0.0935,
      "track_valence": 0.356,
      "track_tempo": 173.963,
      "track_time_signature": 3
    },
    {
      "track_name": "Rabbit",
      "track_popularity": 4,
      "track_preview": "https://p.scdn.co/mp3-preview/19b5352f7f9c2052fff21251b82cbf3251bc7296?cid=5bae1e05720d486a8bef2310f63cdb05",
      "track_duration": 263658,
      "track_danceability": 0.353,
      "track_energy": 0.137,
      "track_key": 11,
      "track_loudness": -16.341,
      "track_mode": 0,
      "track_speechiness": 0.0311,
      "track_acousticness": 0.812,
      "track_instrumentalness": 0.0643,
      "track_liveness": 0.0963,
      "track_valence": 0.13,
      "track_tempo": 110.614,
      "track_time_signature": 3
    }
  ]
}